README.rst
setup.py
pylacrosse/__init__.py
pylacrosse/cli_tool.py
pylacrosse/lacrosse.py
pylacrosse/version.py
pylacrosse.egg-info/PKG-INFO
pylacrosse.egg-info/SOURCES.txt
pylacrosse.egg-info/dependency_links.txt
pylacrosse.egg-info/entry_points.txt
pylacrosse.egg-info/requires.txt
pylacrosse.egg-info/top_level.txt
tests/__init__.py
tests/test_lacrosse.py