Metadata-Version: 1.1
Name: pylacrosse
Version: 0.3.1
Summary: LaCrosse sensor library
Home-page: http://github.com/hthiery/python-lacrosse
Author: Heiko Thiery
Author-email: heiko.thiery@gmail.com
License: LGPLv2+
Platform: UNKNOWN
Classifier: Development Status :: 3 - Alpha
Classifier: Environment :: Console
Classifier: License :: OSI Approved :: GNU Lesser General Public License v2 or later (LGPLv2+)
Classifier: Natural Language :: English
Classifier: Operating System :: OS Independent
Classifier: Programming Language :: Python :: 2
Classifier: Programming Language :: Python :: 2.7
Classifier: Programming Language :: Python :: 3
Classifier: Programming Language :: Python :: 3.4
Classifier: Programming Language :: Python :: 3.5
Classifier: Topic :: Software Development :: Libraries :: Python Modules
